{
  "version": "1",
  "cognitoConfig": {
    "identityPoolName": "inboxflowai47c67166_identitypool_47c67166",
    "allowUnauthenticatedIdentities": false,
    "resourceNameTruncated": "inboxf47c67166",
    "userPoolName": "inboxflowai47c67166_userpool_47c67166",
    "autoVerifiedAttributes": [
      "email"
    ],
    "mfaConfiguration": "OFF",
    "mfaTypes": [
      "SMS Text Message"
    ],
    "smsAuthenticationMessage": "Your authentication code is {####}",
    "smsVerificationMessage": "Your verification code is {####}",
    "emailVerificationSubject": "Your verification code",
    "emailVerificationMessage": "Your verification code is {####}",
    "defaultPasswordPolicy": false,
    "passwordPolicyMinLength": 8,
    "passwordPolicyCharacters": [],
    "requiredAttributes": [
      "email",
      "name"
    ],
    "aliasAttributes": [],
    "userpoolClientGenerateSecret": false,
    "userpoolClientRefreshTokenValidity": 30,
    "userpoolClientWriteAttributes": [
      "email"
    ],
    "userpoolClientReadAttributes": [
      "email"
    ],
    "userpoolClientLambdaRole": "inboxf47c67166_userpoolclient_lambda_role",
    "userpoolClientSetAttributes": false,
    "sharedId": "47c67166",
    "resourceName": "inboxflowai47c67166",
    "authSelections": "identityPoolAndUserPool",
    "useDefault": "default",
    "usernameAttributes": [
      "email"
    ],
    "triggers": {
      "CustomMessage": [
        "verification-link"
      ]
    },
    "userPoolGroupList": [],
    "serviceName": "Cognito",
    "verificationBucketName": "inboxflowai47c67166verificationbucket",
    "usernameCaseSensitive": false,
    "useEnabledMfas": true
  }
}